jcof/__init__.py
jcof/dumping.py
jcof/loading.py
jcof-1.0.1.dist-info/LICENSE
jcof-1.0.1.dist-info/METADATA
jcof-1.0.1.dist-info/WHEEL
jcof-1.0.1.dist-info/top_level.txt
jcof-1.0.1.dist-info/RECORD
