Metadata-Version: 2.1
Name: jcof
Version: 1.0.1
Summary: A Python implementation of JCOF: JSON-like Compact Object Format
Author: WhoAteMyButter
License: GPL-3.0-or-later
Project-URL: Source, https://gitlab.com/whoatembutter/pyjcof
Project-URL: Changelog, https://gitlab.com/whoatemybutter/pyjcof/-/blob/master/CHANGELOG.md
Project-URL: Issue-Tracker, https://gitlab.com/whoatemybutter/pyjcof/-/issues
Keywords: jcof,pyjcof,json,compact json,jsonlike compact object format,json format,json compact,jcofpy
Classifier: Programming Language :: Python :: 3
Classifier: Programming Language :: Python :: 3 :: Only
Classifier: Programming Language :: Python :: 3.10
Classifier: Operating System :: OS Independent
Classifier: Topic :: Utilities
Classifier: Topic :: Other/Nonlisted Topic
Classifier: Development Status :: 3 - Alpha
Classifier: Intended Audience :: Other Audience
Classifier: Intended Audience :: Information Technology
Classifier: Intended Audience :: Developers
Classifier: License :: OSI Approved :: GNU General Public License v3 or later (GPLv3+)
Classifier: Natural Language :: English
Requires-Python: >=3.10
License-File: LICENSE
Provides-Extra: testing
Requires-Dist: pytest (>=5.0.0) ; extra == 'testing'
